src/design/clock_enable.sv
module clock_enable #(
    parameter MAX_COUNT = 10
)(
    input logic clk,
    input logic reset,
    output logic enable
);

logic [$clog2(MAX_COUNT):0] counter;

always_ff @(posedge clk or posedge reset) begin
    if (reset) begin
        counter <= 0;
        enable <= 0;
    end
    else begin
        enable <= 0;
        counter <= counter + 1;

        if (counter == MAX_COUNT-1) begin
            counter <= 0;
            enable <= 1;
        end
    end
end

endmodule

src/sim/tb_clock_enable.sv
module tb_clock_enable;

logic clk;
logic reset;
logic enable;

clock_enable #(.MAX_COUNT(5)) DUT (
    .clk(clk),
    .reset(reset),
    .enable(enable)
);

always #5 clk = ~clk;

initial begin
    clk = 0;
    reset = 1;

    #20;
    reset = 0;

    #200;

    $finish;
end

endmodule

src/build/tb_clock_enable.vcd
$date
	Mon May 04 19:59:50 2026
$end
$version
	Icarus Verilog
$end
$timescale
	1ps
$end
$scope module tb_clock_enable $end
$var wire 1 ! enable $end
$var reg 1 " clk $end
$var reg 1 # reset $end
$scope module DUT $end
$var wire 1 " clk $end
$var wire 1 # reset $end
$var parameter 32 $ MAX_COUNT $end
$var reg 4 % counter [3:0] $end
$var reg 1 ! enable $end
$upscope $end
$upscope $end
$enddefinitions $end
$comment Show the parameter values. $end
$dumpall
b101 $
$end
#0
$dumpvars
b0 %
1#
0"
0!
$end
#5000
1"
#10000
0"
#15000
1"
#20000
0"
0#
#25000
b1 %
1"
#30000
0"
#35000
b10 %
1"
#40000
0"
#45000
b11 %
1"
#50000
0"
#55000
b100 %
1"
#60000
0"
#65000
1!
b0 %
1"
#70000
0"
#75000
b1 %
0!
1"
#80000
0"
#85000
b10 %
1"
#90000
0"
#95000
b11 %
1"
#100000
0"
#105000
b100 %
1"
#110000
0"
#115000
1!
b0 %
1"
#120000
0"
#125000
b1 %
0!
1"
#130000
0"
#135000
b10 %
1"
#140000
0"
#145000
b11 %
1"
#150000
0"
#155000
b100 %
1"
#160000
0"
#165000
1!
b0 %
1"
#170000
0"
#175000
b1 %
0!
1"
#180000
0"
#185000
b10 %
1"
#190000
0"
#195000
b11 %
1"
#200000
0"
#205000
b100 %
1"
#210000
0"
#215000
1!
b0 %
1"
