src/design/debounce.sv
module debounce #(
    parameter LIMIT = 5
)(
    input logic clk,
    input logic reset,
    input logic noisy_in,
    output logic clean_out
);

logic previous;
logic [$clog2(LIMIT):0] counter;

always_ff @(posedge clk or posedge reset) begin
    if (reset) begin
        previous <= 0;
        counter <= 0;
        clean_out <= 0;
    end
    else begin

        if (noisy_in != previous) begin
            counter <= 0;
        end
        else begin
            counter <= counter + 1;
        end

        if (counter == LIMIT-1) begin
            clean_out <= noisy_in;
        end

        previous <= noisy_in;
    end
end

endmodule

src/sim/tb_debounce.sv
module tb_debounce;

logic clk;
logic reset;
logic noisy_in;
logic clean_out;

debounce #(.LIMIT(4)) DUT (
    .clk(clk),
    .reset(reset),
    .noisy_in(noisy_in),
    .clean_out(clean_out)
);

always #5 clk = ~clk;

initial begin
    clk = 0;
    reset = 1;
    noisy_in = 0;

    #20;
    reset = 0;

    // rebote
    #10 noisy_in = 1;
    #10 noisy_in = 0;
    #10 noisy_in = 1;
    #10 noisy_in = 0;
    #10 noisy_in = 1;

    #100;

    $finish;
end

endmodule

src/build/tb_debounce.vcd
$date
	Mon May 04 20:04:32 2026
$end
$version
	Icarus Verilog
$end
$timescale
	1s
$end
$scope module tb_debounce $end
$var wire 1 ! clean_out $end
$var reg 1 " clk $end
$var reg 1 # noisy_in $end
$var reg 1 $ reset $end
$scope module DUT $end
$var wire 1 " clk $end
$var wire 1 # noisy_in $end
$var wire 1 $ reset $end
$var parameter 32 % LIMIT $end
$var reg 1 ! clean_out $end
$var reg 3 & counter [2:0] $end
$var reg 1 ' previous $end
$upscope $end
$upscope $end
$enddefinitions $end
$comment Show the parameter values. $end
$dumpall
b100 %
$end
#0
$dumpvars
0'
b0 &
1$
0#
0"
0!
$end
#5
1"
#10
0"
#15
1"
#20
0"
0$
#25
b1 &
1"
#30
0"
1#
#35
1'
b0 &
1"
#40
0"
0#
#45
0'
1"
#50
0"
1#
#55
1'
1"
#60
0"
0#
#65
0'
1"
#70
0"
1#
#75
1'
1"
#80
0"
#85
b1 &
1"
#90
0"
#95
b10 &
1"
#100
0"
#105
b11 &
1"
#110
0"
#115
1!
b100 &
1"
#120
0"
#125
b101 &
1"
#130
0"
#135
b110 &
1"
#140
0"
#145
b111 &
1"
#150
0"
#155
b0 &
1"
#160
0"
#165
b1 &
1"
