src/design/keypad_reader.sv
module keypad_reader (
    input logic clk,
    input logic reset,
    input logic scan_enable,
    input logic [3:0] rows,

    output logic [3:0] cols,
    output logic [1:0] row_detect,
    output logic [1:0] col_detect,
    output logic key_valid
);

logic [1:0] current_col;

always_ff @(posedge clk or posedge reset) begin

    if (reset) begin
        current_col <= 0;
        cols <= 4'b1110;
        key_valid <= 0;
    end
    else begin

        key_valid <= 0;

        if (scan_enable) begin

            current_col <= current_col + 1;

            case(current_col)
                2'd0: cols <= 4'b1110;
                2'd1: cols <= 4'b1101;
                2'd2: cols <= 4'b1011;
                2'd3: cols <= 4'b0111;
            endcase

            if (rows != 4'b0000) begin

                key_valid <= 1;
                col_detect <= current_col;

                case(rows)
                    4'b0001: row_detect <= 0;
                    4'b0010: row_detect <= 1;
                    4'b0100: row_detect <= 2;
                    4'b1000: row_detect <= 3;
                endcase

            end
        end
    end
end

endmodule

src/sim/tb_keypad_reader.sv
module tb_keypad_reader;

logic clk;
logic reset;
logic scan_enable;
logic [3:0] rows;

logic [3:0] cols;
logic [1:0] row_detect;
logic [1:0] col_detect;
logic key_valid;

keypad_reader DUT(
    .clk(clk),
    .reset(reset),
    .scan_enable(scan_enable),
    .rows(rows),
    .cols(cols),
    .row_detect(row_detect),
    .col_detect(col_detect),
    .key_valid(key_valid)
);

always #5 clk = ~clk;

initial begin

    clk = 0;
    reset = 1;
    scan_enable = 0;
    rows = 0;

    #20;
    reset = 0;

    forever begin
        #20 scan_enable = 1;
        #10 scan_enable = 0;
    end

end

initial begin

    #80;
    rows = 4'b0010;

    #40;
    rows = 0;

    #100;

    $finish;

end

endmodule

src/build/tb_keypad_reader.vcd
$date
	Fri May 15 15:08:34 2026
$end
$version
	Icarus Verilog
$end
$timescale
	1s
$end
$scope module tb_keypad_reader $end
$var wire 2 ! row_detect [1:0] $end
$var wire 1 " key_valid $end
$var wire 4 # cols [3:0] $end
$var wire 2 $ col_detect [1:0] $end
$var reg 1 % clk $end
$var reg 1 & reset $end
$var reg 4 ' rows [3:0] $end
$var reg 1 ( scan_enable $end
$scope module DUT $end
$var wire 1 % clk $end
$var wire 1 & reset $end
$var wire 4 ) rows [3:0] $end
$var wire 1 ( scan_enable $end
$var reg 2 * col_detect [1:0] $end
$var reg 4 + cols [3:0] $end
$var reg 2 , current_col [1:0] $end
$var reg 1 " key_valid $end
$var reg 2 - row_detect [1:0] $end
$upscope $end
$upscope $end
$enddefinitions $end
$comment Show the parameter values. $end
$dumpall
$end
#0
$dumpvars
bx -
b0 ,
b1110 +
bx *
b0 )
0(
b0 '
1&
0%
bx $
b1110 #
0"
bx !
$end
#5
1%
#10
0%
#15
1%
#20
0%
0&
#25
1%
#30
0%
#35
1%
#40
0%
1(
#45
b1 ,
1%
#50
0%
0(
#55
1%
#60
0%
#65
1%
#70
0%
1(
#75
b1101 #
b1101 +
b10 ,
1%
#80
0%
0(
b10 '
b10 )
#85
1%
#90
0%
#95
1%
#100
0%
1(
#105
b1 !
b1 -
b10 $
b10 *
1"
b1011 #
b1011 +
b11 ,
1%
#110
0%
0(
#115
0"
1%
#120
0%
b0 '
b0 )
#125
1%
#130
0%
1(
#135
b111 #
b111 +
b0 ,
1%
#140
0%
0(
#145
1%
#150
0%
#155
1%
#160
0%
1(
#165
b1110 #
b1110 +
b1 ,
1%
#170
0%
0(
#175
1%
#180
0%
#185
1%
#190
0%
1(
#195
b1101 #
b1101 +
b10 ,
1%
#200
0%
0(
#205
1%
#210
0%
#215
1%
#220
0%
1(
