src/design/sync.sv
module sync (
    input logic clk,
    input logic async_in,
    output logic sync_out
);

logic ff1, ff2;

always_ff @(posedge clk) begin
    ff1 <= async_in;
    ff2 <= ff1;
end

assign sync_out = ff2;

endmodule

src/sim/tb_sync.sv
module tb_sync;

logic clk;
logic async_in;
logic sync_out;

sync DUT (
    .clk(clk),
    .async_in(async_in),
    .sync_out(sync_out)
);

always #5 clk = ~clk;

initial begin
    clk = 0;
    async_in = 0;

    #17 async_in = 1;
    #23 async_in = 0;
    #40 async_in = 1;

    #100;

    $finish;
end

endmodule

src/build/tb_sync.vcd
$date
	Mon May 04 20:02:18 2026
$end
$version
	Icarus Verilog
$end
$timescale
	1s
$end
$scope module tb_sync $end
$var wire 1 ! sync_out $end
$var reg 1 " async_in $end
$var reg 1 # clk $end
$scope module DUT $end
$var wire 1 " async_in $end
$var wire 1 # clk $end
$var wire 1 ! sync_out $end
$var reg 1 $ ff1 $end
$var reg 1 % ff2 $end
$upscope $end
$upscope $end
$enddefinitions $end
$comment Show the parameter values. $end
$dumpall
$end
#0
$dumpvars
x%
x$
0#
0"
x!
$end
#5
0$
1#
#10
0#
#15
0!
0%
1#
#17
1"
#20
0#
#25
1$
1#
#30
0#
#35
1!
1%
1#
#40
0#
0"
#45
0$
1#
#50
0#
#55
0!
0%
1#
#60
0#
#65
1#
#70
0#
#75
1#
#80
0#
1"
#85
1$
1#
#90
0#
#95
1!
1%
1#
